progan_h/__init__.py
progan_h/cli.py
progan_h/docs/knn.md
progan_h-0.1.0.dist-info/licenses/LICENSE
progan_h-0.1.0.dist-info/METADATA
progan_h-0.1.0.dist-info/WHEEL
progan_h-0.1.0.dist-info/entry_points.txt
progan_h-0.1.0.dist-info/top_level.txt
progan_h-0.1.0.dist-info/RECORD
